MAGIC/MAGIC.py
MAGIC/__init__.py
XMAItest/MAGIC.py
XMAItest/XMAItest.py
XMAItest/__init__.py
xmaitest-0.1.1.dist-info/LICENSE.txt
xmaitest-0.1.1.dist-info/METADATA
xmaitest-0.1.1.dist-info/WHEEL
xmaitest-0.1.1.dist-info/top_level.txt
xmaitest-0.1.1.dist-info/RECORD
