Metadata-Version: 2.2
Name: XMAItest
Version: 0.1.1
Summary: Small code King AI related library
Home-page: https://github.com/Tonykai88/XMAI.git
Author: pydevelopment
Author-email: hekai@xiaoma.cn
Classifier: Programming Language :: Python :: 3
Classifier: License :: OSI Approved :: MIT License
Classifier: Operating System :: OS Independent
Requires-Python: >=3.7.0
License-File: LICENSE.txt
Requires-Dist: requests>=2.32.3
Dynamic: author
Dynamic: author-email
Dynamic: classifier
Dynamic: description
Dynamic: description-content-type
Dynamic: home-page
Dynamic: requires-dist
Dynamic: requires-python
Dynamic: summary
